pwtest/__init__.py
pwtest/cli.py
pwtest/conftest.py
pwtest/py.typed
pwtest/pytest.ini
pwtest/config/__init__.py
pwtest/config/config_base.py
pwtest/utils/__init__.py
pwtest/utils/browser_state_manager.py
pwtest/utils/env_info.py
pwtest-1.0.1.dist-info/licenses/LICENSE
pwtest-1.0.1.dist-info/METADATA
pwtest-1.0.1.dist-info/WHEEL
pwtest-1.0.1.dist-info/entry_points.txt
pwtest-1.0.1.dist-info/top_level.txt
pwtest-1.0.1.dist-info/RECORD
