Metadata-Version: 2.4
Name: pwtest
Version: 1.0.1
Summary: 基于 Playwright + Pytest + Allure 的 UI 自动化测试框架
Author-email: mofanx <yanwuning@live.cn>
Maintainer-email: mofanx <yanwuning@live.cn>
License-Expression: MIT
Project-URL: Homepage, https://github.com/mofanx/pwtest
Project-URL: Documentation, https://github.com/mofanx/pwtest/blob/main/README.md
Project-URL: Repository, https://github.com/mofanx/pwtest
Project-URL: Bug Reports, https://github.com/mofanx/pwtest/issues
Project-URL: Changelog, https://github.com/mofanx/pwtest/blob/main/CHANGELOG.md
Keywords: playwright,pytest,automation,testing,ui-testing,allure,test-framework,e2e-testing
Classifier: Development Status :: 4 - Beta
Classifier: Framework :: Pytest
Classifier: Intended Audience :: Developers
Classifier: Topic :: Software Development :: Testing
Classifier: Topic :: Software Development :: Quality Assurance
Classifier: Programming Language :: Python :: 3
Classifier: Programming Language :: Python :: 3.8
Classifier: Programming Language :: Python :: 3.9
Classifier: Programming Language :: Python :: 3.10
Classifier: Programming Language :: Python :: 3.11
Classifier: Programming Language :: Python :: 3.12
Classifier: Operating System :: OS Independent
Requires-Python: >=3.8
License-File: LICENSE
Requires-Dist: playwright>=1.54.0
Requires-Dist: pytest>=8.4.1
Requires-Dist: pytest-playwright>=0.7.0
Requires-Dist: loguru>=0.7.3
Requires-Dist: allure-pytest>=2.15.0
Provides-Extra: dev
Requires-Dist: pytest-html>=4.1.1; extra == "dev"
Requires-Dist: build>=1.0.0; extra == "dev"
Requires-Dist: twine>=4.0.0; extra == "dev"
Requires-Dist: black>=23.0.0; extra == "dev"
Requires-Dist: flake8>=6.0.0; extra == "dev"
Requires-Dist: mypy>=1.0.0; extra == "dev"
Provides-Extra: all
Requires-Dist: pwtest[dev]; extra == "all"
Dynamic: license-file
